hebrew-special-numbers-default.yml
hebrew_numbers/__init__.py
hebrew_numbers/tests.py
python_hebrew_numbers-0.2.3.dist-info/DESCRIPTION.rst
python_hebrew_numbers-0.2.3.dist-info/METADATA
python_hebrew_numbers-0.2.3.dist-info/RECORD
python_hebrew_numbers-0.2.3.dist-info/WHEEL
python_hebrew_numbers-0.2.3.dist-info/metadata.json
python_hebrew_numbers-0.2.3.dist-info/top_level.txt
