Metadata-Version: 1.0
Name: python-hebrew-numbers
Version: 0.2.3
Summary: conversion of hebrew numbers (Gimatria)
Home-page: https://github.com/OriHoch/python-hebrew-numbers
Author: Ori Hoch
Author-email: ori@uumpa.com
License: MIT
Platform: UNKNOWN
